eve_s3storage/__init__.py
eve_s3storage/s3_file.py
eve_s3storage/s3_storage.py
eve_s3storage/tests/__init__.py
eve_s3storage/tests/test_s3_storage.py
eve_s3storage/tests/utils.py
eve_s3storage-0.3.dist-info/LICENSE
eve_s3storage-0.3.dist-info/METADATA
eve_s3storage-0.3.dist-info/WHEEL
eve_s3storage-0.3.dist-info/top_level.txt
eve_s3storage-0.3.dist-info/RECORD
