Metadata-Version: 2.1
Name: eve-s3storage
Version: 0.3
Summary: python-eve S3 MediaStorage extension
Home-page: https://gitlab.ethz.ch/amiv/eve-s3storage
Author: Sandro Lutz
Author-email: code@temparus.ch
License: ISC License
Requires-Dist: minio
Requires-Dist: eve
